hierts/__init__.py
hierts/reconciliation.py
hierts/_old/reconciliation.py
hierts-0.9.0.dist-info/LICENSE
hierts-0.9.0.dist-info/METADATA
hierts-0.9.0.dist-info/WHEEL
hierts-0.9.0.dist-info/top_level.txt
hierts-0.9.0.dist-info/RECORD
