Metadata-Version: 2.1
Name: hierts
Version: 0.9.0
Summary: Hierarchical time series reconciliation
Author-email: Olivier Sprangers <o.r.sprangers@uva.nl>
License: Apache License
Project-URL: Source, https://github.com/elephaint/hierts
Project-URL: Documentation, https://hierts.readthedocs.io/en/latest/index.html
Classifier: Programming Language :: Python :: 3
Classifier: License :: OSI Approved :: Apache Software License
Classifier: Operating System :: OS Independent
Requires-Python: >=3.7
License-File: LICENSE
Requires-Dist: pandas >=1.3.5
Requires-Dist: numba >=0.53.0
Requires-Dist: scipy >=1.7.3
Requires-Dist: scikit-learn >=1.0.2
Requires-Dist: polars >=0.19.3
